howso/__main__.py
howso/client/__init__.py
howso/client/base.py
howso/client/cache.py
howso/client/client.py
howso/client/configuration.py
howso/client/exceptions.py
howso/client/protocols.py
howso/client/pandas/__init__.py
howso/client/pandas/client.py
howso/direct/__init__.py
howso/direct/_utilities.py
howso/direct/client.py
howso/direct/core.py
howso/engine/__init__.py
howso/engine/client.py
howso/engine/project.py
howso/engine/session.py
howso/engine/trainee.py
howso/howso-engine/howso.caml
howso/howso-engine/trainee_template.caml
howso/howso-engine/version.json
howso/howso-engine/migrations/migrations.caml
howso/scikit/__init__.py
howso/scikit/scikit.py
howso/utilities/__init__.py
howso/utilities/features.py
howso/utilities/installation_verification.py
howso/utilities/internals.py
howso/utilities/json_wrapper.py
howso/utilities/locale.py
howso/utilities/monitors.py
howso/utilities/posix.py
howso/utilities/random.py
howso/utilities/testing.py
howso/utilities/utilities.py
howso/utilities/feature_attributes/__init__.py
howso/utilities/feature_attributes/base.py
howso/utilities/feature_attributes/infer_feature_attributes.py
howso/utilities/feature_attributes/pandas.py
howso/utilities/feature_attributes/protocols.py
howso/utilities/feature_attributes/relational.py
howso/utilities/feature_attributes/time_series.py
howso_engine_api-7.0.5.dist-info/LICENSE-3RD-PARTY.txt
howso_engine_api-7.0.5.dist-info/LICENSE.txt
howso_engine_api-7.0.5.dist-info/METADATA
howso_engine_api-7.0.5.dist-info/WHEEL
howso_engine_api-7.0.5.dist-info/entry_points.txt
howso_engine_api-7.0.5.dist-info/top_level.txt
howso_engine_api-7.0.5.dist-info/RECORD
