Metadata-Version: 2.1
Name: howso-engine-api
Version: 7.0.5
Summary: Howso Engine and Scikit Estimator for the interpretable Machine Learning and Artificial Intelligence API.
Author: Howso Incorporated
Author-email: support@howso.com
License: Diveplane Corporation
Project-URL: homepage, https://howso.com
Project-URL: documentation, https://docs.community.howso.com/
Project-URL: repository, https://github.com/howsoai/howso-engine-api-py
Keywords: machine,learning,artificial,intelligence
Classifier: Development Status :: 3 - Alpha
Classifier: Intended Audience :: Science/Research
Classifier: Topic :: Scientific/Engineering :: Artificial Intelligence
Classifier: License :: Other/Proprietary License
Classifier: Programming Language :: Python :: 3
Classifier: Programming Language :: Python :: 3.8
Classifier: Programming Language :: Python :: 3.9
Classifier: Programming Language :: Python :: 3.10
Classifier: Programming Language :: Python :: 3.11
Classifier: Operating System :: MacOS
Classifier: Operating System :: MacOS :: MacOS X
Classifier: Operating System :: Microsoft :: Windows
Classifier: Operating System :: Microsoft :: Windows :: Windows 10
Classifier: Operating System :: Microsoft :: Windows :: Windows 11
Classifier: Operating System :: POSIX :: Linux
Requires-Python: >=3.8
License-File: LICENSE-3RD-PARTY.txt
License-File: LICENSE.txt
Requires-Dist: certifi
Requires-Dist: cryptography (>=2.9.2)
Requires-Dist: deprecation (<3,>=2.1.0)
Requires-Dist: Faker (>=4.1.1)
Requires-Dist: humanize (>=4.0.0)
Requires-Dist: mmh3
Requires-Dist: numpy
Requires-Dist: pandas
Requires-Dist: pyjwt (<3,>=2.6.0)
Requires-Dist: pyyaml (<7.0,>=6.0.1)
Requires-Dist: rich (>=12.5.1)
Requires-Dist: scikit-learn
Requires-Dist: semantic-version (<3,>=2.8.5)
Requires-Dist: typing-extensions (<5.0,>=4.1.0)
Requires-Dist: urllib3 (<=2,>=1.26.2)
Requires-Dist: howso-openapi-client (==24.0.15)
Requires-Dist: amalgam-lang (==2.3.18)
Provides-Extra: dev
Requires-Dist: dill (<1.0,>=0.3.4) ; extra == 'dev'
Requires-Dist: flake8-docstrings ; extra == 'dev'
Requires-Dist: flake8-import-order ; extra == 'dev'
Requires-Dist: flake8 (<4.0,>=3.7) ; extra == 'dev'
Requires-Dist: pip-tools ; extra == 'dev'
Requires-Dist: pipdeptree ; extra == 'dev'
Requires-Dist: pmlb ; extra == 'dev'
Requires-Dist: pycodestyle ; extra == 'dev'
Requires-Dist: pylint ; extra == 'dev'
Requires-Dist: pytest ; extra == 'dev'
Requires-Dist: pytest-cov ; extra == 'dev'
Requires-Dist: pytest-mock (<1.14.0,>=1.13.0) ; extra == 'dev'
Requires-Dist: urllib3 (<2.0.0) ; extra == 'dev'
Provides-Extra: no-telemetry
Requires-Dist: howso-engine-no-telemetry ; extra == 'no-telemetry'
